treetag/__init__.py
treetag/_init_tree.py
treetag/convert.py
treetag/doublets.py
treetag/markers.py
treetag/plotting.py
treetag/scoring.py
treetag/tagger.py
treetag/utils.py
treetag/data/PBMC_markers.yaml
treetag/data/PBMC_tree.yaml
treetag/data/__init__.py
treetag-0.1.1.dist-info/licenses/LICENSE
treetag-0.1.1.dist-info/METADATA
treetag-0.1.1.dist-info/WHEEL
treetag-0.1.1.dist-info/top_level.txt
treetag-0.1.1.dist-info/RECORD
