Metadata-Version: 2.4
Name: treetag
Version: 0.1.1
Summary: Hierarchical cell-type tagging with YAML ontologies and markers.
Author-email: Guy Shakhar <guy.shakhar@gmail.com>
License: MIT
Project-URL: Homepage, https://github.com/valleyofdawn/TreeTag
Project-URL: Repository, https://github.com/valleyofdawn/TreeTag
Project-URL: Issues, https://github.com/valleyofdawn/TreeTag/issues
Keywords: single-cell,bioinformatics,annotation,scanpy
Classifier: Development Status :: 3 - Alpha
Classifier: Programming Language :: Python :: 3
Classifier: Programming Language :: Python :: 3.10
Classifier: Programming Language :: Python :: 3.11
Classifier: Programming Language :: Python :: 3.12
Classifier: License :: OSI Approved :: MIT License
Classifier: Intended Audience :: Science/Research
Classifier: Topic :: Scientific/Engineering :: Bio-Informatics
Requires-Python: >=3.10
License-File: LICENSE
Requires-Dist: pyyaml>=6
Requires-Dist: python-igraph>=0.11
Requires-Dist: numpy>=1.26
Requires-Dist: pandas>=2.0
Requires-Dist: scipy>=1.11
Requires-Dist: scanpy>=1.10
Dynamic: license-file
